bandsos/__init__.py
bandsos/color.py
bandsos/gfs.py
bandsos/post.py
bandsos/schism.py
bandsos/webdata.py
bandsos/webdir.py
bandsos-0.5.dist-info/LICENSE
bandsos-0.5.dist-info/WHEEL
bandsos-0.5.dist-info/METADATA
bandsos-0.5.dist-info/RECORD
