Metadata-Version: 2.1
Name: bandsos
Version: 0.5
Summary: .. danger::
Keywords: flood,forecasting,schism,gfs,hwrf
Author-email: Jamal Khan <jamal919@gmail.com>
Requires-Python: >=3.7
Classifier: License :: OSI Approved :: GNU General Public License v3 or later (GPLv3+)
Requires-Dist: requests
Requires-Dist: numpy
Requires-Dist: scipy
Requires-Dist: matplotlib
Requires-Dist: pandas
Requires-Dist: xarray
Requires-Dist: utide
Requires-Dist: cmocean
Requires-Dist: rioxarray
Project-URL: Home, https://jamalkhan.me/bandsos
Project-URL: Repo, https://github.com/jamal919/bandsos-platform
